open_this/socialMedia.py
open_this-1.0.1.dist-info/LICENSE
open_this-1.0.1.dist-info/METADATA
open_this-1.0.1.dist-info/WHEEL
open_this-1.0.1.dist-info/entry_points.txt
open_this-1.0.1.dist-info/top_level.txt
open_this-1.0.1.dist-info/RECORD
