Metadata-Version: 2.1
Name: open-this
Version: 1.0.1
Summary: A Python tiny package that opens Facebook, Youtube from terminal
Home-page: https://github.com/iamdarshan7/OpenSocialMediaWithCLI
Author: Darshan Thapa
Author-email: darshanthapa872@gmail.com
License: MIT
Platform: UNKNOWN
Classifier: License :: OSI Approved :: MIT License
Classifier: Programming Language :: Python :: 3
Classifier: Programming Language :: Python :: 3.7
Requires-Dist: pyperclip (==1.8.0)
